{"tour":[{"libelle":"Poule 6 - tour n°1 du 07\/02\/2026","equa":"CHAMPAGNE TT 4","equb":"TT ST GENIS LAVAL 3","scorea":"29","scoreb":"25","lien":"renc_id=5917947&is_retour=0&phase=2&res_1=29&res_2=25&equip_1=CHAMPAGNE+TT+4&equip_2=TT+ST+GENIS+LAVAL+3&equip_id1=10583&equip_id2=9508&clubnum_1=01690112&clubnum_2=01690107","dateprevue":"07\/02\/2026","datereelle":"07\/02\/2026"},{"libelle":"Poule 6 - tour n°1 du 07\/02\/2026","equa":"AL IRIGNY TT 2","equb":"AL VAISE SERIN 2","scorea":"18","scoreb":"0","lien":"renc_id=5917948&is_retour=0&phase=2&res_1=18&res_2=0&equip_1=AL+IRIGNY+TT+2&equip_2=AL+VAISE+SERIN+2&equip_id1=8922&equip_id2=10147&clubnum_1=01690201&clubnum_2=01690062","dateprevue":"07\/02\/2026","datereelle":"08\/02\/2026"},{"libelle":"Poule 6 - tour n°1 du 07\/02\/2026","equa":"Club Pongiste PUSIGNAN 2","equb":"AS GREZIEU TT 1","scorea":"28","scoreb":"26","lien":"renc_id=5917949&is_retour=0&phase=2&res_1=28&res_2=26&equip_1=Club+Pongiste+PUSIGNAN+2&equip_2=AS+GREZIEU+TT+1&equip_id1=15023&equip_id2=9371&clubnum_1=01690211&clubnum_2=01690185","dateprevue":"07\/02\/2026","datereelle":"07\/02\/2026"},{"libelle":"Poule 6 - tour n°1 du 07\/02\/2026","equa":"VILLEFRANCHE TTCAV 8","equb":"JA CALUIRE 1","scorea":"26","scoreb":"28","lien":"renc_id=5917950&is_retour=0&phase=2&res_1=26&res_2=28&equip_1=VILLEFRANCHE+TTCAV+8&equip_2=JA+CALUIRE+1&equip_id1=27247&equip_id2=10148&clubnum_1=01690023&clubnum_2=01690047","dateprevue":"07\/02\/2026","datereelle":"07\/02\/2026"},{"libelle":"Poule 6 - tour n°2 du 07\/03\/2026","equa":"AL VAISE SERIN 2","equb":"CHAMPAGNE TT 4","scorea":"28","scoreb":"26","lien":"renc_id=5917951&is_retour=0&phase=2&res_1=28&res_2=26&equip_1=AL+VAISE+SERIN+2&equip_2=CHAMPAGNE+TT+4&equip_id1=10147&equip_id2=10583&clubnum_1=01690062&clubnum_2=01690112","dateprevue":"07\/03\/2026","datereelle":"07\/03\/2026"},{"libelle":"Poule 6 - tour n°2 du 07\/03\/2026","equa":"AS GREZIEU TT 1","equb":"AL IRIGNY TT 2","scorea":"23","scoreb":"31","lien":"renc_id=5917952&is_retour=0&phase=2&res_1=23&res_2=31&equip_1=AS+GREZIEU+TT+1&equip_2=AL+IRIGNY+TT+2&equip_id1=9371&equip_id2=8922&clubnum_1=01690185&clubnum_2=01690201","dateprevue":"07\/03\/2026","datereelle":"08\/03\/2026"},{"libelle":"Poule 6 - tour n°2 du 07\/03\/2026","equa":"JA CALUIRE 1","equb":"Club Pongiste PUSIGNAN 2","scorea":"36","scoreb":"18","lien":"renc_id=5917953&is_retour=0&phase=2&res_1=36&res_2=18&equip_1=JA+CALUIRE+1&equip_2=Club+Pongiste+PUSIGNAN+2&equip_id1=10148&equip_id2=15023&clubnum_1=01690047&clubnum_2=01690211","dateprevue":"07\/03\/2026","datereelle":"08\/03\/2026"},{"libelle":"Poule 6 - tour n°2 du 07\/03\/2026","equa":"TT ST GENIS LAVAL 3","equb":"VILLEFRANCHE TTCAV 8","scorea":"31","scoreb":"23","lien":"renc_id=5917954&is_retour=0&phase=2&res_1=31&res_2=23&equip_1=TT+ST+GENIS+LAVAL+3&equip_2=VILLEFRANCHE+TTCAV+8&equip_id1=9508&equip_id2=27247&clubnum_1=01690107&clubnum_2=01690023","dateprevue":"07\/03\/2026","datereelle":"08\/03\/2026"},{"libelle":"Poule 6 - tour n°3 du 21\/03\/2026","equa":"CHAMPAGNE TT 4","equb":"AS GREZIEU TT 1","scorea":"32","scoreb":"22","lien":"renc_id=5917955&is_retour=0&phase=2&res_1=32&res_2=22&equip_1=CHAMPAGNE+TT+4&equip_2=AS+GREZIEU+TT+1&equip_id1=10583&equip_id2=9371&clubnum_1=01690112&clubnum_2=01690185","dateprevue":"21\/03\/2026","datereelle":"21\/03\/2026"},{"libelle":"Poule 6 - tour n°3 du 21\/03\/2026","equa":"AL IRIGNY TT 2","equb":"JA CALUIRE 1","scorea":"21","scoreb":"33","lien":"renc_id=5917956&is_retour=0&phase=2&res_1=21&res_2=33&equip_1=AL+IRIGNY+TT+2&equip_2=JA+CALUIRE+1&equip_id1=8922&equip_id2=10148&clubnum_1=01690201&clubnum_2=01690047","dateprevue":"21\/03\/2026","datereelle":"22\/03\/2026"},{"libelle":"Poule 6 - tour n°3 du 21\/03\/2026","equa":"Club Pongiste PUSIGNAN 2","equb":"VILLEFRANCHE TTCAV 8","scorea":"19","scoreb":"35","lien":"renc_id=5917957&is_retour=0&phase=2&res_1=19&res_2=35&equip_1=Club+Pongiste+PUSIGNAN+2&equip_2=VILLEFRANCHE+TTCAV+8&equip_id1=15023&equip_id2=27247&clubnum_1=01690211&clubnum_2=01690023","dateprevue":"21\/03\/2026","datereelle":"21\/03\/2026"},{"libelle":"Poule 6 - tour n°3 du 21\/03\/2026","equa":"TT ST GENIS LAVAL 3","equb":"AL VAISE SERIN 2","scorea":"22","scoreb":"32","lien":"renc_id=5917958&is_retour=0&phase=2&res_1=22&res_2=32&equip_1=TT+ST+GENIS+LAVAL+3&equip_2=AL+VAISE+SERIN+2&equip_id1=9508&equip_id2=10147&clubnum_1=01690107&clubnum_2=01690062","dateprevue":"21\/03\/2026","datereelle":"22\/03\/2026"},{"libelle":"Poule 6 - tour n°4 du 18\/04\/2026","equa":"JA CALUIRE 1","equb":"CHAMPAGNE TT 4","scorea":"28","scoreb":"26","lien":"renc_id=5917959&is_retour=0&phase=2&res_1=28&res_2=26&equip_1=JA+CALUIRE+1&equip_2=CHAMPAGNE+TT+4&equip_id1=10148&equip_id2=10583&clubnum_1=01690047&clubnum_2=01690112","dateprevue":"18\/04\/2026","datereelle":"19\/04\/2026"},{"libelle":"Poule 6 - tour n°4 du 18\/04\/2026","equa":"VILLEFRANCHE TTCAV 8","equb":"AL IRIGNY TT 2","scorea":"28","scoreb":"26","lien":"renc_id=5917960&is_retour=0&phase=2&res_1=28&res_2=26&equip_1=VILLEFRANCHE+TTCAV+8&equip_2=AL+IRIGNY+TT+2&equip_id1=27247&equip_id2=8922&clubnum_1=01690023&clubnum_2=01690201","dateprevue":"18\/04\/2026","datereelle":"18\/04\/2026"},{"libelle":"Poule 6 - tour n°4 du 18\/04\/2026","equa":"Club Pongiste PUSIGNAN 2","equb":"TT ST GENIS LAVAL 3","scorea":"25","scoreb":"29","lien":"renc_id=5917961&is_retour=0&phase=2&res_1=25&res_2=29&equip_1=Club+Pongiste+PUSIGNAN+2&equip_2=TT+ST+GENIS+LAVAL+3&equip_id1=15023&equip_id2=9508&clubnum_1=01690211&clubnum_2=01690107","dateprevue":"18\/04\/2026","datereelle":"18\/04\/2026"},{"libelle":"Poule 6 - tour n°4 du 18\/04\/2026","equa":"AS GREZIEU TT 1","equb":"AL VAISE SERIN 2","scorea":"25","scoreb":"29","lien":"renc_id=5917962&is_retour=0&phase=2&res_1=25&res_2=29&equip_1=AS+GREZIEU+TT+1&equip_2=AL+VAISE+SERIN+2&equip_id1=9371&equip_id2=10147&clubnum_1=01690185&clubnum_2=01690062","dateprevue":"18\/04\/2026","datereelle":"19\/04\/2026"},{"libelle":"Poule 6 - tour n°5 du 09\/05\/2026","equa":"CHAMPAGNE TT 4","equb":"VILLEFRANCHE TTCAV 8","scorea":{},"scoreb":{},"lien":"renc_id=5917963&is_retour=0&phase=2&res_1=&res_2=&equip_1=CHAMPAGNE+TT+4&equip_2=VILLEFRANCHE+TTCAV+8&equip_id1=10583&equip_id2=27247&clubnum_1=01690112&clubnum_2=01690023","dateprevue":"09\/05\/2026","datereelle":"09\/05\/2026"},{"libelle":"Poule 6 - tour n°5 du 09\/05\/2026","equa":"AL IRIGNY TT 2","equb":"Club Pongiste PUSIGNAN 2","scorea":{},"scoreb":{},"lien":"renc_id=5917964&is_retour=0&phase=2&res_1=&res_2=&equip_1=AL+IRIGNY+TT+2&equip_2=Club+Pongiste+PUSIGNAN+2&equip_id1=8922&equip_id2=15023&clubnum_1=01690201&clubnum_2=01690211","dateprevue":"09\/05\/2026","datereelle":"09\/05\/2026"},{"libelle":"Poule 6 - tour n°5 du 09\/05\/2026","equa":"AL VAISE SERIN 2","equb":"JA CALUIRE 1","scorea":{},"scoreb":{},"lien":"renc_id=5917965&is_retour=0&phase=2&res_1=&res_2=&equip_1=AL+VAISE+SERIN+2&equip_2=JA+CALUIRE+1&equip_id1=10147&equip_id2=10148&clubnum_1=01690062&clubnum_2=01690047","dateprevue":"09\/05\/2026","datereelle":"09\/05\/2026"},{"libelle":"Poule 6 - tour n°5 du 09\/05\/2026","equa":"TT ST GENIS LAVAL 3","equb":"AS GREZIEU TT 1","scorea":{},"scoreb":{},"lien":"renc_id=5917966&is_retour=0&phase=2&res_1=&res_2=&equip_1=TT+ST+GENIS+LAVAL+3&equip_2=AS+GREZIEU+TT+1&equip_id1=9508&equip_id2=9371&clubnum_1=01690107&clubnum_2=01690185","dateprevue":"09\/05\/2026","datereelle":"09\/05\/2026"},{"libelle":"Poule 6 - tour n°6 du 30\/05\/2026","equa":"Club Pongiste PUSIGNAN 2","equb":"CHAMPAGNE TT 4","scorea":{},"scoreb":{},"lien":"renc_id=5917967&is_retour=0&phase=2&res_1=&res_2=&equip_1=Club+Pongiste+PUSIGNAN+2&equip_2=CHAMPAGNE+TT+4&equip_id1=15023&equip_id2=10583&clubnum_1=01690211&clubnum_2=01690112","dateprevue":"30\/05\/2026","datereelle":"30\/05\/2026"},{"libelle":"Poule 6 - tour n°6 du 30\/05\/2026","equa":"AL IRIGNY TT 2","equb":"TT ST GENIS LAVAL 3","scorea":{},"scoreb":{},"lien":"renc_id=5917968&is_retour=0&phase=2&res_1=&res_2=&equip_1=AL+IRIGNY+TT+2&equip_2=TT+ST+GENIS+LAVAL+3&equip_id1=8922&equip_id2=9508&clubnum_1=01690201&clubnum_2=01690107","dateprevue":"30\/05\/2026","datereelle":"30\/05\/2026"},{"libelle":"Poule 6 - tour n°6 du 30\/05\/2026","equa":"VILLEFRANCHE TTCAV 8","equb":"AL VAISE SERIN 2","scorea":{},"scoreb":{},"lien":"renc_id=5917969&is_retour=0&phase=2&res_1=&res_2=&equip_1=VILLEFRANCHE+TTCAV+8&equip_2=AL+VAISE+SERIN+2&equip_id1=27247&equip_id2=10147&clubnum_1=01690023&clubnum_2=01690062","dateprevue":"30\/05\/2026","datereelle":"30\/05\/2026"},{"libelle":"Poule 6 - tour n°6 du 30\/05\/2026","equa":"JA CALUIRE 1","equb":"AS GREZIEU TT 1","scorea":{},"scoreb":{},"lien":"renc_id=5917970&is_retour=0&phase=2&res_1=&res_2=&equip_1=JA+CALUIRE+1&equip_2=AS+GREZIEU+TT+1&equip_id1=10148&equip_id2=9371&clubnum_1=01690047&clubnum_2=01690185","dateprevue":"30\/05\/2026","datereelle":"30\/05\/2026"},{"libelle":"Poule 6 - tour n°7 du 06\/06\/2026","equa":"CHAMPAGNE TT 4","equb":"AL IRIGNY TT 2","scorea":{},"scoreb":{},"lien":"renc_id=5917971&is_retour=0&phase=2&res_1=&res_2=&equip_1=CHAMPAGNE+TT+4&equip_2=AL+IRIGNY+TT+2&equip_id1=10583&equip_id2=8922&clubnum_1=01690112&clubnum_2=01690201","dateprevue":"06\/06\/2026","datereelle":"06\/06\/2026"},{"libelle":"Poule 6 - tour n°7 du 06\/06\/2026","equa":"AL VAISE SERIN 2","equb":"Club Pongiste PUSIGNAN 2","scorea":{},"scoreb":{},"lien":"renc_id=5917972&is_retour=0&phase=2&res_1=&res_2=&equip_1=AL+VAISE+SERIN+2&equip_2=Club+Pongiste+PUSIGNAN+2&equip_id1=10147&equip_id2=15023&clubnum_1=01690062&clubnum_2=01690211","dateprevue":"06\/06\/2026","datereelle":"06\/06\/2026"},{"libelle":"Poule 6 - tour n°7 du 06\/06\/2026","equa":"AS GREZIEU TT 1","equb":"VILLEFRANCHE TTCAV 8","scorea":{},"scoreb":{},"lien":"renc_id=5917973&is_retour=0&phase=2&res_1=&res_2=&equip_1=AS+GREZIEU+TT+1&equip_2=VILLEFRANCHE+TTCAV+8&equip_id1=9371&equip_id2=27247&clubnum_1=01690185&clubnum_2=01690023","dateprevue":"06\/06\/2026","datereelle":"06\/06\/2026"},{"libelle":"Poule 6 - tour n°7 du 06\/06\/2026","equa":"TT ST GENIS LAVAL 3","equb":"JA CALUIRE 1","scorea":{},"scoreb":{},"lien":"renc_id=5917974&is_retour=0&phase=2&res_1=&res_2=&equip_1=TT+ST+GENIS+LAVAL+3&equip_2=JA+CALUIRE+1&equip_id1=9508&equip_id2=10148&clubnum_1=01690107&clubnum_2=01690047","dateprevue":"06\/06\/2026","datereelle":"06\/06\/2026"}]}